kbrainsecurity/azure_authentication.py
kbrainsecurity/bearer.py
kbrainsecurity-0.3.2.dist-info/LICENSE.md
kbrainsecurity-0.3.2.dist-info/METADATA
kbrainsecurity-0.3.2.dist-info/WHEEL
kbrainsecurity-0.3.2.dist-info/RECORD
