Metadata-Version: 2.1
Name: kbrainsecurity
Version: 0.3.2
Summary: Security and authentication functions for use in KBRAIN
License: AGPLv3
Author: Daniel E. Fredriksen
Author-email: daniel.fredriksen@us.kbr.com
Requires-Python: >=3.10,<4.0
Classifier: License :: Other/Proprietary License
Classifier: Programming Language :: Python :: 3
Classifier: Programming Language :: Python :: 3.10
Classifier: Programming Language :: Python :: 3.11
Requires-Dist: azure-functions (>=1.15.0,<2.0.0)
Requires-Dist: python-jose (>=3.3.0,<4.0.0)
